treegrams/__init__.py
treegrams/angularl.py
treegrams/angularr.py
treegrams/cstripes.py
treegrams/extratools.py
treegrams/fgram.py
treegrams/hline.py
treegrams/lstripes.py
treegrams/pqgram.py
treegrams/raingram.py
treegrams/raingraml.py
treegrams/raingramr.py
treegrams/rstripes.py
treegrams/squareanglel.py
treegrams/squareanglelf.py
treegrams/squareangler.py
treegrams/squareanglerf.py
treegrams/stripes.py
treegrams/tgram.py
treegrams/threestripes.py
treegrams/transformers.py
treegrams/treegram.py
treegrams/vgram.py
treegrams-0.1.0.dist-info/LICENSE
treegrams-0.1.0.dist-info/WHEEL
treegrams-0.1.0.dist-info/METADATA
treegrams-0.1.0.dist-info/RECORD
