Metadata-Version: 2.1
Name: treegrams
Version: 0.1.0
Summary: Extracts sub-tree patterns from NLTK tree structures.
Author: Benjamin Murauer
Author-email: b.murauer@posteo.de
Requires-Python: >=3.6,<4
Classifier: Programming Language :: Python :: 3
Classifier: Programming Language :: Python :: 3.6
Classifier: Programming Language :: Python :: 3.7
Classifier: Programming Language :: Python :: 3.8
Classifier: Programming Language :: Python :: 3.9
Requires-Dist: nltk (>=3.5,<4.0)
Requires-Dist: sklearn (>=0.0,<0.1)
